{
  "tokens": [
    {
      "id": 0,
      "description": "Genesis Number",
      "external_url": "https://www.google.com/search?q=genesis+number",
      "image": "https://twemoji.maxcdn.com/svg/1f366.svg",
      "name": "My NFT 0"
    },
    {
      "id": 1,
      "description": "AON Genesis",
      "external_url": "https://www.google.com/search?q=AON",
      "image": "https://twemoji.maxcdn.com/svg/1f366.svg",
      "name": "First AON Test Collection NFT"
    },
    {
      "id": 2,
      "description": "AON Genesis",
      "external_url": "https://www.google.com/search?q=AON",
      "image": "https://twemoji.maxcdn.com/svg/1f367.svg",
      "name": "Second AON Test Collection NFT"
    }
  ]
}
